{"nodes":[{"nodeID":"713","text":"it is hardly more than a business magazine by and for the defense industry.","type":"I","timestamp":"2012-04-12 18:19:48"},{"nodeID":"714","text":"If the defense industry is the sole sponsor of a magazine and if the magazine repeatedly refers to the developments made by the defense industry it is by definition hardly more than a business magazine by and for the defense industry.","type":"I","timestamp":"2012-04-12 18:19:48"},{"nodeID":"715","text":"The defense industry is the sole sponsor of the magazine  Seapower  and  it repeatedly refers to the developments made by the defense industry","type":"I","timestamp":"2012-04-12 18:19:48"},{"nodeID":"716","text":"these corporate sponsors basically are the defense industry","type":"I","timestamp":"2012-04-12 18:19:48"},{"nodeID":"717","text":"The list of  corporate sponsors  include (among its  Gold Medal members ) Lockheed-Martin Rockwell General Dynamics Grumman GE etc. with glossy full-page ads advertising their latest cutting-edge developments.","type":"I","timestamp":"2012-04-12 18:19:48"},{"nodeID":"718","text":"these corporate sponsors are the *only* advertisers in the magazine.","type":"I","timestamp":"2012-04-12 18:19:48"},{"nodeID":"719","text":"The articles themselves make repeated references to the technological developments of these corporations.","type":"I","timestamp":"2012-04-12 18:19:49"},{"nodeID":"720","text":"RA","type":"RA","timestamp":"2012-04-12 18:19:49"},{"nodeID":"721","text":"RA","type":"RA","timestamp":"2012-04-12 18:19:49"}],"edges":[{"edgeID":"649","fromID":"714","toID":"720","formEdgeID":null},{"edgeID":"650","fromID":"715","toID":"720","formEdgeID":null},{"edgeID":"651","fromID":"720","toID":"713","formEdgeID":null},{"edgeID":"652","fromID":"716","toID":"721","formEdgeID":null},{"edgeID":"653","fromID":"717","toID":"721","formEdgeID":null},{"edgeID":"654","fromID":"718","toID":"721","formEdgeID":null},{"edgeID":"655","fromID":"719","toID":"721","formEdgeID":null},{"edgeID":"656","fromID":"721","toID":"715","formEdgeID":null}]}