{"nodes":[{"nodeID":"5424","text":"he is a good athlete","type":"I","timestamp":"2012-04-12 18:35:46"},{"nodeID":"5425","text":"Lendl is a great tennis player","type":"I","timestamp":"2012-04-12 18:35:46"},{"nodeID":"5426","text":"Great tennis players are generally good athletes","type":"I","timestamp":"2012-04-12 18:35:47"},{"nodeID":"5427","text":"RA","type":"RA","timestamp":"2012-04-12 18:35:47"}],"edges":[{"edgeID":"5079","fromID":"5425","toID":"5427","formEdgeID":null},{"edgeID":"5080","fromID":"5426","toID":"5427","formEdgeID":null},{"edgeID":"5081","fromID":"5427","toID":"5424","formEdgeID":null}]}